ArcusModbus.py
ArcusModbus-0.2.8.dist-info/METADATA
ArcusModbus-0.2.8.dist-info/WHEEL
ArcusModbus-0.2.8.dist-info/top_level.txt
ArcusModbus-0.2.8.dist-info/RECORD
