Metadata-Version: 2.1
Name: ArcusModbus
Version: 0.2.8
Summary: Titan IMX servo controller
Author: Daniel Curtis
Author-email: dwc00012@mix.wvu.edu
Keywords: python,Arcus Titan IMX
Classifier: Operating System :: Microsoft :: Windows
Classifier: Programming Language :: Python :: 3
Requires-Dist: pymodbus
